{"errors":[],"warnings":[],"namedChunkGroups":{"app":{"chunks":[10,0,3],"assets":["webpack-runtime-84c0a4b4eba0e9b6c2f5.js","webpack-runtime-84c0a4b4eba0e9b6c2f5.js.map","styles.bfe320d96219a181fd27.css","styles-f845b704d7958f5ff1e4.js","styles-f845b704d7958f5ff1e4.js.map","app-cf597300d8de98d76710.js","app-cf597300d8de98d76710.js.map"],"children":{},"childAssets":{}},"component---src-pages-404-js":{"chunks":[0,4],"assets":["styles.bfe320d96219a181fd27.css","styles-f845b704d7958f5ff1e4.js","styles-f845b704d7958f5ff1e4.js.map","component---src-pages-404-js-4bdc8e101f4451a43607.js","component---src-pages-404-js-4bdc8e101f4451a43607.js.map"],"children":{},"childAssets":{}},"component---src-pages-about-js":{"chunks":[0,2,5],"assets":["styles.bfe320d96219a181fd27.css","styles-f845b704d7958f5ff1e4.js","styles-f845b704d7958f5ff1e4.js.map","2-26dd52a43fb57f7e5061.js","2-26dd52a43fb57f7e5061.js.map","component---src-pages-about-js-7af8e5529a6302061ddd.js","component---src-pages-about-js-7af8e5529a6302061ddd.js.map"],"children":{},"childAssets":{}},"component---src-pages-art-js":{"chunks":[0,1,6],"assets":["styles.bfe320d96219a181fd27.css","styles-f845b704d7958f5ff1e4.js","styles-f845b704d7958f5ff1e4.js.map","1-27fd0a10d9037cf9b820.js","1-27fd0a10d9037cf9b820.js.map","component---src-pages-art-js-9b498c6323119b16b677.js","component---src-pages-art-js-9b498c6323119b16b677.js.map"],"children":{},"childAssets":{}},"component---src-pages-gamedev-js":{"chunks":[0,7],"assets":["styles.bfe320d96219a181fd27.css","styles-f845b704d7958f5ff1e4.js","styles-f845b704d7958f5ff1e4.js.map","component---src-pages-gamedev-js-f3cd2e245969314f5585.js","component---src-pages-gamedev-js-f3cd2e245969314f5585.js.map"],"children":{},"childAssets":{}},"component---src-pages-index-js":{"chunks":[0,2,1,8],"assets":["styles.bfe320d96219a181fd27.css","styles-f845b704d7958f5ff1e4.js","styles-f845b704d7958f5ff1e4.js.map","2-26dd52a43fb57f7e5061.js","2-26dd52a43fb57f7e5061.js.map","1-27fd0a10d9037cf9b820.js","1-27fd0a10d9037cf9b820.js.map","component---src-pages-index-js-3c93a4cf0a959d4c7b70.js","component---src-pages-index-js-3c93a4cf0a959d4c7b70.js.map"],"children":{},"childAssets":{}},"component---src-pages-webdev-js":{"chunks":[0,9],"assets":["styles.bfe320d96219a181fd27.css","styles-f845b704d7958f5ff1e4.js","styles-f845b704d7958f5ff1e4.js.map","component---src-pages-webdev-js-e6b7b171fed1eb7cfe7f.js","component---src-pages-webdev-js-e6b7b171fed1eb7cfe7f.js.map"],"children":{},"childAssets":{}}},"assetsByChunkName":{"app":["webpack-runtime-84c0a4b4eba0e9b6c2f5.js","styles.bfe320d96219a181fd27.css","styles-f845b704d7958f5ff1e4.js","app-cf597300d8de98d76710.js"],"component---src-pages-404-js":["styles.bfe320d96219a181fd27.css","styles-f845b704d7958f5ff1e4.js","component---src-pages-404-js-4bdc8e101f4451a43607.js"],"component---src-pages-about-js":["styles.bfe320d96219a181fd27.css","styles-f845b704d7958f5ff1e4.js","2-26dd52a43fb57f7e5061.js","component---src-pages-about-js-7af8e5529a6302061ddd.js"],"component---src-pages-art-js":["styles.bfe320d96219a181fd27.css","styles-f845b704d7958f5ff1e4.js","1-27fd0a10d9037cf9b820.js","component---src-pages-art-js-9b498c6323119b16b677.js"],"component---src-pages-gamedev-js":["styles.bfe320d96219a181fd27.css","styles-f845b704d7958f5ff1e4.js","component---src-pages-gamedev-js-f3cd2e245969314f5585.js"],"component---src-pages-index-js":["styles.bfe320d96219a181fd27.css","styles-f845b704d7958f5ff1e4.js","2-26dd52a43fb57f7e5061.js","1-27fd0a10d9037cf9b820.js","component---src-pages-index-js-3c93a4cf0a959d4c7b70.js"],"component---src-pages-webdev-js":["styles.bfe320d96219a181fd27.css","styles-f845b704d7958f5ff1e4.js","component---src-pages-webdev-js-e6b7b171fed1eb7cfe7f.js"]}}